st_justgage/__init__.py
st_justgage/frontend/build/asset-manifest.json
st_justgage/frontend/build/bootstrap.min.css
st_justgage/frontend/build/index.html
st_justgage/frontend/build/precache-manifest.119ff7f3ab2bea184458d049a550bbb8.js
st_justgage/frontend/build/precache-manifest.6101b30ca21180ee52042aade843ee19.js
st_justgage/frontend/build/precache-manifest.c3fe7821f1b0d12c03e05dcb8fc2833a.js
st_justgage/frontend/build/precache-manifest.f5a2fdd3612bf1e2a0a4de125b0fce44.js
st_justgage/frontend/build/service-worker.js
st_justgage/frontend/build/static/js/2.335e0532.chunk.js
st_justgage/frontend/build/static/js/2.335e0532.chunk.js.LICENSE.txt
st_justgage/frontend/build/static/js/2.335e0532.chunk.js.map
st_justgage/frontend/build/static/js/2.f541e246.chunk.js
st_justgage/frontend/build/static/js/2.f541e246.chunk.js.LICENSE.txt
st_justgage/frontend/build/static/js/2.f541e246.chunk.js.map
st_justgage/frontend/build/static/js/main.2bc47964.js
st_justgage/frontend/build/static/js/main.2bc47964.js.LICENSE.txt
st_justgage/frontend/build/static/js/main.2bc47964.js.map
st_justgage/frontend/build/static/js/main.428a166c.chunk.js
st_justgage/frontend/build/static/js/main.428a166c.chunk.js.map
st_justgage/frontend/build/static/js/main.65285eee.chunk.js
st_justgage/frontend/build/static/js/main.65285eee.chunk.js.map
st_justgage/frontend/build/static/js/main.bf038373.chunk.js
st_justgage/frontend/build/static/js/main.bf038373.chunk.js.map
st_justgage/frontend/build/static/js/main.de7e88aa.chunk.js
st_justgage/frontend/build/static/js/main.de7e88aa.chunk.js.map
st_justgage/frontend/build/static/js/runtime-main.eff8f9d2.js
st_justgage/frontend/build/static/js/runtime-main.eff8f9d2.js.map
st_justgage-0.2.3.dist-info/LICENSE
st_justgage-0.2.3.dist-info/METADATA
st_justgage-0.2.3.dist-info/WHEEL
st_justgage-0.2.3.dist-info/top_level.txt
st_justgage-0.2.3.dist-info/RECORD
