Metadata-Version: 2.1
Name: st-justgage
Version: 0.2.3
Summary: Streamlit Component for justGage Charts
Author: 
Author-email: 
Requires-Python: >=3.6
License-File: LICENSE
Requires-Dist: streamlit >=0.63
